{
  "bodies": [],
  "description": "Traveling Vortice Pair",
  "drawparams": {
    "backgroundColor": [
      0.0,
      0.0,
      0.0,
      1.0
    ],
    "density": 0.3499999940395355,
    "featureColor": [
      0.800000011920929,
      0.800000011920929,
      0.800000011920929,
      1.0
    ],
    "negativeColor": [
      0.250980406999588,
      0.250980406999588,
      1.0,
      1.0
    ],
    "positiveColor": [
      0.6941176652908325,
      0.1568627506494522,
      0.1568627506494522,
      1.0
    ],
    "tracerScale": 0.15000000596046448,
    "viewPoint": [
      -0.5,
      0.0
    ],
    "viewScale": 2.0,
    "vortonScale": 1.0,
    "windowSize": [
      1252,
      950
    ]
  },
  "flowparams": {
    "Re": 255.99998474121094,
    "Uinf": [
      0.0,
      0.0
    ]
  },
  "flowstructures": [
    {
      "center": [
        0.0,
        0.5
      ],
      "enabled": true,
      "radius": 0.30000001192092896,
      "softness": 0.10000000149011612,
      "strength": 1.0,
      "type": "vortex blob"
    },
    {
      "center": [
        0.0,
        -0.5
      ],
      "enabled": true,
      "radius": 0.30000001192092896,
      "softness": 0.10000000149011612,
      "strength": -1.0,
      "type": "vortex blob"
    }
  ],
  "simparams": {
    "VRM": {
      "ignoreBelow": 9.999999747378752e-06,
      "relativeThresholds": true
    },
    "nominalDt": 0.019999999552965164,
    "outputDt": 0.0,
    "viscous": "none"
  },
  "version": {
    "Omega2D": 1,
    "jsonInput": 1
  }
}
